lr35902dis/__init__.py
lr35902dis/lr35902.py
lr35902dis-1.0.2.dist-info/LICENSE
lr35902dis-1.0.2.dist-info/METADATA
lr35902dis-1.0.2.dist-info/WHEEL
lr35902dis-1.0.2.dist-info/top_level.txt
lr35902dis-1.0.2.dist-info/RECORD
