Metadata-Version: 2.1
Name: lr35902dis
Version: 1.0.2
Summary: lr35902 (GameBoy CPU) disassembler library
Home-page: https://github.com/Lukas-Dresel/lr35902dis
Author: Lukas Dresel
Author-email: foo@bar.com
License: UNKNOWN
Platform: UNKNOWN
Classifier: Programming Language :: Python :: 3
Classifier: License :: OSI Approved :: MIT License
Classifier: Operating System :: OS Independent
Classifier: Topic :: Games/Entertainment
Classifier: Topic :: Software Development :: Disassemblers
License-File: LICENSE
